{
  "$schema": "http://json-schema.org/draft-04/schema#",
  "type": "object",
  "properties": {
    "@id": {
      "type": "string",
      "format": "uri",
      "description": "Unique identifier in the source system"
    },
    "id": {
      "type": "string",
      "description": "Unique identifier in the source system"
    },
    "identifiers": {
      "type": "string",
      "description": "Array of unique URN identifiers"
    },
    "name": {
      "type": "string",
      "description": "Display name for the site"
    },
    "featureCatalog": {
      "type": "string",
      "format": "uri",
      "dltype": "[FeatureCatalogItem](FeatureCatalogItem.md)",
      "description": "Url for getting list of catalog items with features(refer to [MapsFeatureCatalog](MapsFeatureCatalog.md) on a site"
    },
    "dateModified": {
      "type": "string",
      "description": "ISO8601 date format 2018-07-19T23:00:08+00:00. Date when details were last modified. Bubles up from Feature Catalog"
    }
  }
}
